{
    "_id": "7094",
    "name": "7094 Argyle Calf Length",
    "brand": "Jockey",
    "category": 0,
    "price": 0,
    "description": "Elastane body\n\u00a9 StayFresh technology",
    "size": [
        "ONE SIZE"
    ],
    "colors": [
        "Available",
        "in",
        "Assorted",
        "Colours",
        "Mid",
        "Grey",
        "Mel,",
        ">",
        "Green",
        "Mel.",
        "eww"
    ],
    "images": [
        "public/images/product/Socks/13/product.png",
        "public/images/product/Socks/13/colors.png"
    ]
}